twitter.common.http-0.3.11-py2.7-nspkg.pth
twitter/common/http/__init__.py
twitter/common/http/diagnostics.py
twitter/common/http/plugin.py
twitter/common/http/server.py
twitter.common.http-0.3.11.dist-info/DESCRIPTION.rst
twitter.common.http-0.3.11.dist-info/METADATA
twitter.common.http-0.3.11.dist-info/RECORD
twitter.common.http-0.3.11.dist-info/WHEEL
twitter.common.http-0.3.11.dist-info/metadata.json
twitter.common.http-0.3.11.dist-info/namespace_packages.txt
twitter.common.http-0.3.11.dist-info/top_level.txt
twitter.common.http-0.3.11.dist-info/zip-safe
