Metadata-Version: 2.0
Name: twitter.common.http
Version: 0.3.11
Summary: twitter.common wrappers for bottle and simple diagnostics endpoints.
Home-page: https://github.com/twitter/commons
Author: UNKNOWN
Author-email: UNKNOWN
License: Apache License, Version 2.0
Platform: UNKNOWN
Classifier: Intended Audience :: Developers
Classifier: License :: OSI Approved :: Apache Software License
Classifier: Operating System :: OS Independent
Classifier: Programming Language :: Python
Requires-Dist: bottle (==0.11.6)
Requires-Dist: twitter.common.lang (==0.3.11)
Requires-Dist: twitter.common.log (==0.3.11)
